{
  "updatedAt": "2026-05-08T18:38:12.864Z",
  "items": [
    {
      "id": "1233532",
      "title": "Tierseuchenallgemeinverfügung zur Vorbeugung vor der Einschleppung und der frühzeitigen Erkennung der Newcastle Disease (ND)",
      "url": "https://www.gemeinde-roederland.de/news/1/1233532/nachrichten/tierseuchenallgemeinverfügung-zur-vorbeugung-vor-der-einschleppung-und-der-frühzeitigen-erkennung-der-newcastle-disease-nd.html",
      "description": "Anordnung präventiver Maßnahmen aufgrund einer Vielzahl von Ausbrüchen der Newcastle Disease Seit Februar 2026 wurden in Geflügelhaltungen in Brandenburg eine Vielzahl von Ausbrüchen der ...  [mehr]",
      "fetchedAt": "2026-05-08T18:37:39.639Z",
      "publishedAt": "2026-05-08T00:00:00.000Z",
      "updatedAt": "2026-05-08T18:38:12.863Z"
    },
    {
      "id": "1219486",
      "title": "Gemeindeverwaltung geschlossen",
      "url": "https://www.gemeinde-roederland.de/news/1/1219486/nachrichten/gemeindeverwaltung-geschlossen.html",
      "description": "Am Freitag, dem 15. Mai 2026 bleibt die Verwaltung geschlossen! [mehr]",
      "fetchedAt": "2026-05-08T18:37:39.639Z",
      "publishedAt": "2026-04-07T00:00:00.000Z",
      "updatedAt": "2026-05-08T18:38:12.863Z"
    },
    {
      "id": "1211829",
      "title": "Engagement-Wettbewerb „machen!2026“ ist gestartet",
      "url": "https://www.gemeinde-roederland.de/news/1/1211829/nachrichten/engagement-wettbewerb-machen2026-ist-gestartet.html",
      "description": "Der Engagement-Wettbewerb „machen!2026“ ist am 3. März 2026 gestartet. Der Wettbewerb würdigt und unterstützt das vielfältige bürgerschaftliche Engagement Ostdeutschlands in kleineren ...  [mehr]",
      "fetchedAt": "2026-05-08T18:37:39.639Z",
      "publishedAt": "2026-03-18T00:00:00.000Z",
      "updatedAt": "2026-05-08T18:38:12.863Z"
    },
    {
      "id": "1200433",
      "title": "Wichtige Hinweise zur Stichwahl zur Landratswahl",
      "url": "https://www.gemeinde-roederland.de/news/1/1200433/nachrichten/wichtige-hinweise-zur-stichwahl-zur-landratswahl.html",
      "description": "Am 01.03.2026 findet von 08:00 Uhr bis 18:00 Uhr die Stichwahl zum Landrat des Landkreises Elbe-Elster statt.       Bitte beachten Sie folgende Hinweise:   1. Sie haben am 15.02.2026 per ...  [mehr]",
      "fetchedAt": "2026-05-08T18:37:39.639Z",
      "publishedAt": "2026-02-19T00:00:00.000Z",
      "updatedAt": "2026-05-08T18:38:12.863Z"
    },
    {
      "id": "1196950",
      "title": "Änderung der Gebühren für Personalausweise",
      "url": "https://www.gemeinde-roederland.de/news/1/1196950/nachrichten/änderung-der-gebühren-für-personalausweise.html",
      "description": "Bitte beachten Sie, dass sich die Gebühren für die Ausstellung von Personalausweisen am 09.02.2026 geändert haben. •    Personalausweis: 46,00 Euro (10 Jahre gültig) ...  [mehr]",
      "fetchedAt": "2026-05-08T18:37:39.639Z",
      "publishedAt": "2026-02-11T00:00:00.000Z",
      "updatedAt": "2026-05-08T18:38:12.863Z"
    },
    {
      "id": "1178814",
      "title": "Stellenausschreibung des Wasser- und Abwasserverbandes Elsterwerda",
      "url": "https://www.gemeinde-roederland.de/news/1/1178814/nachrichten/stellenausschreibung-des-wasser-und-abwasserverbandes-elsterwerda.html",
      "description": "Der Wasser- und Abwasserverband sucht zum nächstmöglichen Zeitpunkt einen Gruppenleiter für Beiträge und Gebühren (m/w/d).    Die vollständige Stellenausschreibung finden Sie unter folgendem ...  [mehr]",
      "fetchedAt": "2026-05-08T18:37:39.639Z",
      "publishedAt": "2025-12-22T00:00:00.000Z",
      "updatedAt": "2026-05-08T18:38:12.863Z"
    },
    {
      "id": "1168495",
      "title": "Gemeindeverwaltung geschlossen",
      "url": "https://www.gemeinde-roederland.de/news/1/1168495/nachrichten/gemeindeverwaltung-geschlossen.html",
      "description": "Am Freitag, dem 2. Januar 2026 bleibt die Verwaltung geschlossen! [mehr]",
      "fetchedAt": "2026-05-08T18:37:39.639Z",
      "publishedAt": "2025-12-04T00:00:00.000Z",
      "updatedAt": "2026-05-08T18:38:12.863Z"
    },
    {
      "id": "1166552",
      "title": "Trinkwasserunterbrechung in Wainsdorf",
      "url": "https://www.gemeinde-roederland.de/news/1/1166552/nachrichten/trinkwasserunterbrechung-in-wainsdorf.html",
      "description": "Der Wasser- und Abwasserverband Elsterwerda informiert:   Im Rahmen der Wasserverlustsuche kommt es vom 01. bis 05.12.2025 in den Ortschaften Wainsdorf und Thalberg zu kurzzeitigen Unterbrechungen ...  [mehr]",
      "fetchedAt": "2026-05-08T18:37:39.639Z",
      "publishedAt": "2025-12-01T00:00:00.000Z",
      "updatedAt": "2026-05-08T18:38:12.863Z"
    },
    {
      "id": "1166547",
      "title": "Tierseuchenallgemeinverfügung zum Schutz gegen die aviäre Influenza im Landkreis Elbe-Elster",
      "url": "https://www.gemeinde-roederland.de/news/1/1166547/nachrichten/tierseuchenallgemeinverfügung-zum-schutz-gegen-die-aviäre-influenza-im-landkreis-elbe-elster.html",
      "description": "Anordnung präventiver Maßnahmen aufgrund der anhaltenden Geflügelpest-Situation bei Wildvögeln und des erhöhten Eintragsrisikos für Hausgeflügelbestände Die Lage der Geflügelpest-Situation ...  [mehr]",
      "fetchedAt": "2026-05-08T18:37:39.639Z",
      "publishedAt": "2025-12-01T00:00:00.000Z",
      "updatedAt": "2026-05-08T18:38:12.863Z"
    },
    {
      "id": "1161257",
      "title": "Achtung! Unterbrechung der Stromversorgung in Prösen",
      "url": "https://www.gemeinde-roederland.de/news/1/1161257/nachrichten/achtung-unterbrechung-der-stromversorgung-in-prösen.html",
      "description": "Der Stromnetzbetreiber MITNETZ Strom informiert:   Sehr geehrte Kundin, sehr geehrter Kunde, wegen betriebsnotwendiger Arbeiten an unseren Netzanlagen wird die Stromversorgung (Anschlussnutzung) ...  [mehr]",
      "fetchedAt": "2026-05-08T18:37:39.639Z",
      "publishedAt": "2025-11-24T00:00:00.000Z",
      "updatedAt": "2026-05-08T18:38:12.863Z"
    },
    {
      "id": "1148531",
      "title": "Geflügel muss im Stall bleiben – Veranstaltungen untersagt",
      "url": "https://www.gemeinde-roederland.de/news/1/1148531/nachrichten/geflügel-muss-im-stall-bleiben--veranstaltungen-untersagt.html",
      "description": "Geflügelpest im Landkreis Elbe-Elster: Aufstallungspflicht ab dem 29. Oktober 2025    Amt für Veterinärwesen erlässt Tierseuchen-Allgemeinverfügung wegen H5N1-Nachweis bei Wildvögeln   Die ...  [mehr]",
      "fetchedAt": "2026-05-08T18:37:39.639Z",
      "publishedAt": "2025-10-29T00:00:00.000Z",
      "updatedAt": "2026-05-08T18:38:12.863Z"
    },
    {
      "id": "1117382",
      "title": "Bundesweiter Warntag 2025",
      "url": "https://www.gemeinde-roederland.de/news/1/1117382/nachrichten/bundesweiter-warntag-2025.html",
      "description": "Am 11. September 2025 findet der „Bundesweite Warntag 2025“ statt. Anlässlich des Warntages werden alle vorhandenen Warnmultiplikatoren und Warnmittel ausgelöst und so die Funktionsfähigkeit ...  [mehr]",
      "fetchedAt": "2026-05-08T18:37:39.639Z",
      "publishedAt": "2025-09-09T00:00:00.000Z",
      "updatedAt": "2026-05-08T18:38:12.863Z"
    },
    {
      "id": "1116154",
      "title": "Achtung! Unterbrechung der Stromversorgung in Prösen",
      "url": "https://www.gemeinde-roederland.de/news/1/1116154/nachrichten/achtung-unterbrechung-der-stromversorgung-in-prösen.html",
      "description": "Der Stromnetzbetreiber MITNETZ Strom informiert:   Sehr geehrte Kundin, sehr geehrter Kunde, wegen betriebsnotwendiger Arbeiten an unseren Netzanlagen wird die Stromversorgung (Anschlussnutzung)   ...  [mehr]",
      "fetchedAt": "2026-05-08T18:37:39.639Z",
      "publishedAt": "2025-09-05T00:00:00.000Z",
      "updatedAt": "2026-05-08T18:38:12.863Z"
    },
    {
      "id": "1114660",
      "title": "Achtung! Unterbrechung der Stromversorgung in Saathain",
      "url": "https://www.gemeinde-roederland.de/news/1/1114660/nachrichten/achtung-unterbrechung-der-stromversorgung-in-saathain.html",
      "description": "Der Stromnetzbetreiber MITNETZ Strom informiert:   Sehr geehrte Kundin, sehr geehrter Kunde, wegen betriebsnotwendiger Arbeiten an unseren Netzanlagen wird die Stromversorgung (Anschlussnutzung)   ...  [mehr]",
      "fetchedAt": "2026-05-08T18:37:39.639Z",
      "publishedAt": "2025-09-02T00:00:00.000Z",
      "updatedAt": "2026-05-08T18:38:12.863Z"
    },
    {
      "id": "1086925",
      "title": "SG Bürgerdienste geschlossen",
      "url": "https://www.gemeinde-roederland.de/news/1/1086925/nachrichten/sg-bürgerdienste-geschlossen.html",
      "description": "Am Montag, dem 14.07.2025  bleibt das Einwohnermeldeamt / Ordnungsamt  der Gemeinde Röderland  aus technischen Gründen geschlossen!   [mehr]",
      "fetchedAt": "2026-05-08T18:37:39.639Z",
      "publishedAt": "2025-06-27T00:00:00.000Z",
      "updatedAt": "2026-05-08T18:38:12.863Z"
    },
    {
      "id": "1083196",
      "title": "Aufruf Ideenwettbewerbe Ehrenamt",
      "url": "https://www.gemeinde-roederland.de/news/1/1083196/nachrichten/aufruf-ideenwettbewerbe-ehrenamt.html",
      "description": "Projekte für 4. Ideenwettbewerb „Zukunft Ehrenamt“ gesucht   Kreative Ideen zur Stärkung des Ehrenamtes und inklusives Engagement sind gefragt, wenn der von der Staatskanzlei ausgelobte ...  [mehr]",
      "fetchedAt": "2026-05-08T18:37:39.639Z",
      "publishedAt": "2025-06-17T00:00:00.000Z",
      "updatedAt": "2026-05-08T18:38:12.863Z"
    },
    {
      "id": "1074300",
      "title": "Achtung! Unterbrechung der Stromversorgung in Würdenhain",
      "url": "https://www.gemeinde-roederland.de/news/1/1074300/nachrichten/achtung-unterbrechung-der-stromversorgung-in-würdenhain.html",
      "description": "Der Stromnetzbetreiber MITNETZ Strom informiert:   Sehr geehrte Kundin, sehr geehrter Kunde,   am Montag, dem 2. Juni 2025 von 07:00 bis 08:00 Uhr und von 14:00 Uhr bis ca. 16.00 Uhr erfolgen ...  [mehr]",
      "fetchedAt": "2026-05-08T18:37:39.639Z",
      "publishedAt": "2025-05-22T00:00:00.000Z",
      "updatedAt": "2026-05-08T18:38:12.863Z"
    },
    {
      "id": "1070387",
      "title": "Wichtige Info zum Glasfaserausbau",
      "url": "https://www.gemeinde-roederland.de/news/1/1070387/nachrichten/wichtige-info-zum-glasfaserausbau.html",
      "description": "Bis Ende 2028 erhalten über 25.000 Adressen im Landkreis Elbe-Elster einen Glasfaseranschluss im Rahmen des geförderten Breitbandausbaus. In der Gemeinde Röderland baut die GlasfaserPlus GmbH das ...  [mehr]",
      "fetchedAt": "2026-05-08T18:37:39.639Z",
      "publishedAt": "2025-05-13T00:00:00.000Z",
      "updatedAt": "2026-05-08T18:38:12.863Z"
    },
    {
      "id": "1062449",
      "title": "Gemeindeverwaltung geschlossen",
      "url": "https://www.gemeinde-roederland.de/news/1/1062449/nachrichten/gemeindeverwaltung-geschlossen.html",
      "description": "Am Freitag, dem 30. Mai 2025 bleibt die Verwaltung geschlossen! [mehr]",
      "fetchedAt": "2026-05-08T18:37:39.639Z",
      "publishedAt": "2025-05-12T00:00:00.000Z",
      "updatedAt": "2026-05-08T18:38:12.863Z"
    },
    {
      "id": "1045836",
      "title": "Brandenburger Naturschutzpreis",
      "url": "https://www.gemeinde-roederland.de/news/1/1045836/nachrichten/brandenburger-naturschutzpreis.html",
      "description": "Die Stiftung Natur Schutz Fonds Brandenburg lobt den Brandenburger Naturschutzpreis 2025 aus und sucht dafür Kinder, Jugendliche und Erwachsene, die sich besonders für Brandenburgs Natur, ...  [mehr]",
      "fetchedAt": "2026-05-08T18:37:39.639Z",
      "publishedAt": "2025-03-20T00:00:00.000Z",
      "updatedAt": "2026-05-08T18:38:12.863Z"
    },
    {
      "id": "1043131",
      "title": "machen!2025",
      "url": "https://www.gemeinde-roederland.de/news/1/1043131/nachrichten/machen2025.html",
      "description": "Es ist wieder soweit: Der Engagement-Wettbewerb \"machen!2025\" ist am 12. März gestartet.   Bis zum 15. Mai 2025 können Engagierte und Ehrenamtliche aus den ostdeutschen Bundesländern ihre Ideen ...  [mehr]",
      "fetchedAt": "2026-05-08T18:37:39.639Z",
      "publishedAt": "2025-03-14T00:00:00.000Z",
      "updatedAt": "2026-05-08T18:38:12.863Z"
    },
    {
      "id": "1041369",
      "title": "Bauarbeiten an der Ferngasleitung (FGL) 106",
      "url": "https://www.gemeinde-roederland.de/news/1/1041369/nachrichten/bauarbeiten-an-der-ferngasleitung-fgl-106.html",
      "description": "Im Auftrag der ONTRAS Gastransport GmbH (ONTRAS) führen Spezialisten planmäßig von März bis Juni 2025 Bauarbeiten an der Ferngasleitung (FGL) 106 bei Bad Liebenwerda durch.   Damit diese ...  [mehr]",
      "fetchedAt": "2026-05-08T18:37:39.639Z",
      "publishedAt": "2025-03-11T00:00:00.000Z",
      "updatedAt": "2026-05-08T18:38:12.863Z"
    },
    {
      "id": "1030877",
      "title": "Neuerungen bei Ausweisdokumenten",
      "url": "https://www.gemeinde-roederland.de/news/1/1030877/nachrichten/neuerungen-bei-ausweisdokumenten.html",
      "description": "Ab dem 1. Mai 2025 werden ausschließlich digital vorliegende biometrische Lichtbilder für die Beantragung von Personalausweisen, Reisepässen und eID-Karten genutzt. Ausgedruckte Lichtbilder ...  [mehr]",
      "fetchedAt": "2026-05-08T18:37:39.639Z",
      "publishedAt": "2025-02-11T00:00:00.000Z",
      "updatedAt": "2026-05-08T18:38:12.863Z"
    },
    {
      "id": "1030736",
      "title": "Verkehrshinweis zu Baumfällarbeiten entlang der B 169 nach Gröditz",
      "url": "https://www.gemeinde-roederland.de/news/1/1030736/nachrichten/verkehrshinweis-zu-baumfällarbeiten-entlang-der-b-169-nach-gröditz.html",
      "description": "Am 17. Februar 2025 beginnen die Baumfällarbeiten für den Bau eines Geh- und Radweges entlang der B 169 zwischen Gröditz und Prösen.  Die Fällarbeiten sollen voraussichtlich bis 21. Februar ...  [mehr]",
      "fetchedAt": "2026-05-08T18:37:39.639Z",
      "publishedAt": "2025-02-11T00:00:00.000Z",
      "updatedAt": "2026-05-08T18:38:12.863Z"
    },
    {
      "id": "1027061",
      "title": "Sperrung Brücke Reichenhainer Straße - Höhe Baumschule \"Saathainer Mühle\"",
      "url": "https://www.gemeinde-roederland.de/news/1/1027061/nachrichten/sperrung-brücke-reichenhainer-straße-höhe-baumschule-saathainer-mühle.html",
      "description": "Auf Grund von Baustoffuntersuchungen kommt es am 17.02.2025 zur Sperrung an der Brücke „Saathainer Mühle“.  Die Sperrung betrifft nur den 17.02.2025.    Sollten Sie weitere Fragen haben, ...  [mehr]",
      "fetchedAt": "2026-05-08T18:37:39.639Z",
      "publishedAt": "2025-01-31T00:00:00.000Z",
      "updatedAt": "2026-05-08T18:38:12.863Z"
    },
    {
      "id": "1021244",
      "title": "Achtung! Unterbrechung der Stromversorgung in Prösen",
      "url": "https://www.gemeinde-roederland.de/news/1/1021244/nachrichten/achtung-unterbrechung-der-stromversorgung-in-prösen.html",
      "description": "Der Stromnetzbetreiber MITNETZ Strom informiert:   Sehr geehrte Kundin, sehr geehrter Kunde,   wegen betriebsnotwendigen Arbeiten an unseren Netzanlagen wird die Stromversorgung    am Freitag, ...  [mehr]",
      "fetchedAt": "2026-05-08T18:37:39.639Z",
      "publishedAt": "2025-01-16T00:00:00.000Z",
      "updatedAt": "2026-05-08T18:38:12.863Z"
    },
    {
      "id": "1017912",
      "title": "Versorgungsunterbrechung Trinkwasser in Saathain",
      "url": "https://www.gemeinde-roederland.de/news/1/1017912/nachrichten/versorgungsunterbrechung-trinkwasser-in-saathain.html",
      "description": "Der Wasser- und Abwasserverband Elsterwerda teilt mit, dass auf Grund von Reparaturarbeiten an der Trinkwasserleitung am   Mittwoch, dem 08.01.2025 in der Zeit von 8:00 - 16:00 Uhr   kein ...  [mehr]",
      "fetchedAt": "2026-05-08T18:37:39.639Z",
      "publishedAt": "2025-01-07T00:00:00.000Z",
      "updatedAt": "2026-05-08T18:38:12.863Z"
    },
    {
      "id": "971897",
      "title": "Deutsche Glasfaser prüft Glasfaserausbau in Amt Schradenland",
      "url": "https://www.gemeinde-roederland.de/news/1/971897/nachrichten/deutsche-glasfaser-prüft-glasfaserausbau-in-amt-schradenland.html",
      "description": "Deutsche Glasfaser informiert:   Viele Bürgerinnen und Bürger in Gröden, Großthiemig, Hirschfeld und Merzdorf im Amt Schradenland sowie in Prösen und Wainsdorf in der Gemeinde Röderland haben ...  [mehr]",
      "fetchedAt": "2026-05-08T18:37:39.639Z",
      "publishedAt": "2024-08-23T00:00:00.000Z",
      "updatedAt": "2026-05-08T18:38:12.863Z"
    },
    {
      "id": "968956",
      "title": "Achtung! Arbeiten am Stromnetz in Würdenhain",
      "url": "https://www.gemeinde-roederland.de/news/1/968956/nachrichten/achtung-arbeiten-am-stromnetz-in-würdenhain.html",
      "description": "Der Stromnetzbetreiber MITNETZ Strom informiert:   Sehr geehrte Kundin, sehr geehrter Kunde,   am Montag, dem 26. August 2024 von 07:30 bis ca. 08:30 Uhr und von 13:00 bis ca. 14:00 Uhr erfolgen ...  [mehr]",
      "fetchedAt": "2026-05-08T18:37:39.639Z",
      "publishedAt": "2024-08-13T00:00:00.000Z",
      "updatedAt": "2026-05-08T18:38:12.863Z"
    },
    {
      "id": "953172",
      "title": "Hinweis zur Meldung bei Sturmschäden",
      "url": "https://www.gemeinde-roederland.de/news/1/953172/nachrichten/hinweis-zur-meldung-bei-sturmschäden.html",
      "description": "Auf Grund des schweren Sturmes am 18.06.2024 kam es im gesamten Gemeindegebiet vermehrt zu Baumbruch.  Sollte es an Ihrem Eigentum zu Beschädigungen durch Bäume, welche im Eigentum der Gemeinde ...  [mehr]",
      "fetchedAt": "2026-05-08T18:37:39.639Z",
      "publishedAt": "2024-06-20T00:00:00.000Z",
      "updatedAt": "2026-05-08T18:38:12.863Z"
    },
    {
      "id": "947161",
      "title": "Europa- und Kommunalwahl am 09.06.2024",
      "url": "https://www.gemeinde-roederland.de/news/1/947161/nachrichten/europa-und-kommunalwahl-am-09.06.2024.html",
      "description": "Die Ergebnisse für die Europa- und Kommunalwahlen für die Gemeinde Röderland sind nun vollständig im Wahlportal der Gemeinde Röderland nachlesbar.   Zum Wahlportal >>>   [mehr]",
      "fetchedAt": "2026-05-08T18:37:39.639Z",
      "publishedAt": "2024-06-04T00:00:00.000Z",
      "updatedAt": "2026-05-08T18:38:12.863Z"
    },
    {
      "id": "930106",
      "title": "Aufruf zum Kreiswettbewerb „Unser Dorf hat Zukunft“",
      "url": "https://www.gemeinde-roederland.de/news/1/930106/nachrichten/aufruf-zum-kreiswettbewerb-unser-dorf-hat-zukunft.html",
      "description": "Das Ministerium für Landwirtschaft, Umwelt und Klimaschutz und der Städte- und Gemeindebund haben den Aufruf zum 12. Landeswettbewerb „Unser Dorf hat Zukunft“ 2024/2025 gestartet. Im Rahmen ...  [mehr]",
      "fetchedAt": "2026-05-08T18:37:39.639Z",
      "publishedAt": "2024-04-15T00:00:00.000Z",
      "updatedAt": "2026-05-08T18:38:12.863Z"
    },
    {
      "id": "927766",
      "title": "Sperrung Großenhainer Straße aufgrund von Baumaßnahmen",
      "url": "https://www.gemeinde-roederland.de/news/1/927766/nachrichten/sperrung-großenhainer-straße-aufgrund-von-baumaßnahmen.html",
      "description": "Auf Grund der aktuellen Baumaßnahmen zur Erneuerung der Gasfernleitung 12 im Bereich Prösen wird es zur Sperrung der Großenhainer Straße, zwischen Hausnummer 17 und 19a kommen. Dies betrifft vor ...  [mehr]",
      "fetchedAt": "2026-05-08T18:37:39.639Z",
      "publishedAt": "2024-04-08T00:00:00.000Z",
      "updatedAt": "2026-05-08T18:38:12.863Z"
    },
    {
      "id": "922123",
      "title": "Eingeschränkte Trinkwasserversorgung in Reichenhain, Haida, Elsterwerda, Saathain, Hohenleipisch/Dreska, Plessa, Kahla und Döllingen",
      "url": "https://www.gemeinde-roederland.de/news/1/922123/nachrichten/eingeschränkte-trinkwasserversorgung-in-reichenhain-haida-elsterwerda-saathain-hohenleipisch-dreska-plessa-kahla-und-döllingen.html",
      "description": "Aufgrund eines Rohrbruches auf der Trinkwasser-Hauptversorgungsleitung im Bereich Würdenhain kommt es ab sofort zur Unterbrechung der Trinkwasserversorgung im gesamten genannten Versorgungsgebiet. ...  [mehr]",
      "fetchedAt": "2026-05-08T18:37:39.639Z",
      "publishedAt": "2024-03-19T00:00:00.000Z",
      "updatedAt": "2026-05-08T18:38:12.863Z"
    },
    {
      "id": "914520",
      "title": "Straßensperrung L59 Wainsdorf",
      "url": "https://www.gemeinde-roederland.de/news/1/914520/nachrichten/straßensperrung-l59-wainsdorf.html",
      "description": "Aufgrund von Baumaßnamen ist die L59 (Wainsdorf Richtung Gröditz) vom 26.02.2024 bis 15.03.2024 gesperrt.  Eine Umleitung ist ausgeschildert. [mehr]",
      "fetchedAt": "2026-05-08T18:37:39.639Z",
      "publishedAt": "2024-02-27T00:00:00.000Z",
      "updatedAt": "2026-05-08T18:38:12.863Z"
    },
    {
      "id": "914302",
      "title": "Preisträger*innen für Naturschutzpreis 2024 gesucht!",
      "url": "https://www.gemeinde-roederland.de/news/1/914302/nachrichten/preisträger-innen-für-naturschutzpreis-2024-gesucht.html",
      "description": "Sie engagieren sich für Brandenburgs Natur? Bewerben Sie sich für den Naturschutzpreis 2024! [mehr]",
      "fetchedAt": "2026-05-08T18:37:39.639Z",
      "publishedAt": "2024-02-27T00:00:00.000Z",
      "updatedAt": "2026-05-08T18:38:12.863Z"
    },
    {
      "id": "912830",
      "title": "Die Wainsdorfer Hymne",
      "url": "https://www.gemeinde-roederland.de/news/1/912830/nachrichten/die-wainsdorfer-hymne.html",
      "description": "Die Entstehung der \"W a i n s d o r f - H y m n e\"   Zur 600-Jahrfeier unserer Gemeinde Wainsdorf, im Jahr 2006, wurde im Rahmen der Festlichkeiten ein Lied über Wainsdorf erstmalig aufgeführt. ...  [mehr]",
      "fetchedAt": "2026-05-08T18:37:39.639Z",
      "publishedAt": "2024-02-22T00:00:00.000Z",
      "updatedAt": "2026-05-08T18:38:12.863Z"
    },
    {
      "id": "907370",
      "title": "Dorfplatz in Prösen ab 12.02.2024 gesperrt!",
      "url": "https://www.gemeinde-roederland.de/news/1/907370/nachrichten/dorfplatz-in-prösen-ab-12.02.2024-gesperrt.html",
      "description": "Die Gemeindeverwaltung informiert! Aufgrund der Neugestaltung des Dorfplatzes ist dieser ab dem 12. Februar 2024 bis voraussichtlich 9. August 2024 gesperrt.   Die Glascontainer sowie der ...  [mehr]",
      "fetchedAt": "2026-05-08T18:37:39.639Z",
      "publishedAt": "2024-02-05T00:00:00.000Z",
      "updatedAt": "2026-05-08T18:38:12.863Z"
    },
    {
      "id": "898705",
      "title": "Hinweis Zusatzleerung Papiertonne",
      "url": "https://www.gemeinde-roederland.de/news/1/898705/nachrichten/hinweis-zusatzleerung-papiertonne.html",
      "description": "Der AEV Schwarze Elster informiert   Aufgrund der jährlich neuen Tourenplanung  kommt es zu Verschiebungen der Entsorgungstage .   Letzte Entsorgung der Papiertonne war am 06.12.2023 und die ...  [mehr]",
      "fetchedAt": "2026-05-08T18:37:39.639Z",
      "publishedAt": "2024-01-05T00:00:00.000Z",
      "updatedAt": "2026-05-08T18:38:12.863Z"
    },
    {
      "id": "883135",
      "title": "Eisenbahn-Bundesamt startet zweite Phase der Öffentlichkeitsbeteiligung",
      "url": "https://www.gemeinde-roederland.de/news/1/883135/nachrichten/eisenbahn-bundesamt-startet-zweite-phase-der-öffentlichkeitsbeteiligung.html",
      "description": "Am 20. November 2023 veröffentlicht das Eisenbahn-Bundesamt den Entwurf des Lärmaktionsplanes an Schienenwegen des Bundes und die zweite Phase der Öffentlichkeitsbeteiligung der Runde 4 beginnt. ...  [mehr]",
      "fetchedAt": "2026-05-08T18:37:39.639Z",
      "publishedAt": "2023-11-14T00:00:00.000Z",
      "updatedAt": "2026-05-08T18:38:12.863Z"
    },
    {
      "id": "883066",
      "title": "Wichtige Informationen zur Wiederherstellung der Trinkwasserversorgung in Wainsdorf",
      "url": "https://www.gemeinde-roederland.de/news/1/883066/nachrichten/wichtige-informationen-zur-wiederherstellung-der-trinkwasserversorgung-in-wainsdorf.html",
      "description": "Der Wasser- und Abwasserverband Elsterwerda informiert:   Mit dem Vorliegen aller mikrobiologischen und chemischen Analysen erfolgte - wie angekündigt - am Dienstag, dem 07.11.2023 die ...  [mehr]",
      "fetchedAt": "2026-05-08T18:37:39.639Z",
      "publishedAt": "2023-11-14T00:00:00.000Z",
      "updatedAt": "2026-05-08T18:38:12.863Z"
    },
    {
      "id": "878088",
      "title": "Wichtige Informationen zur Trinkwasserversorgung Wainsdorf",
      "url": "https://www.gemeinde-roederland.de/news/1/878088/nachrichten/wichtige-informationen-zur-trinkwasserversorgung-wainsdorf.html",
      "description": "Der Wasser- und Abwasserverband Elsterwerda informiert:   Bis voraussichtlich zum 07.11.2023 wird die provisorische Leitung über die gesamte Länge der neu zu errichtenden Transportleitung in ...  [mehr]",
      "fetchedAt": "2026-05-08T18:37:39.639Z",
      "publishedAt": "2023-10-27T00:00:00.000Z",
      "updatedAt": "2026-05-08T18:38:12.863Z"
    },
    {
      "id": "874446",
      "title": "Tierseuchenallgemeinverfügung über die Anordnung zusätzlicher Maßnahmen zum Schutz gegen die aviäre Influenza",
      "url": "https://www.gemeinde-roederland.de/news/1/874446/nachrichten/tierseuchenallgemeinverfügung-über-die-anordnung-zusätzlicher-maßnahmen-zum-schutz-gegen-die-aviäre-influenza.html",
      "description": "Der Landkreis Elbe-Elster, Amt für Veterinärwesen, Lebensmittelüberwachung und Landwirtschaft erlässt am 29. September 2023 folgende Tierseuchenallgemeinverfügung über die Anordnung ...  [mehr]",
      "fetchedAt": "2026-05-08T18:37:39.639Z",
      "publishedAt": "2023-10-16T00:00:00.000Z",
      "updatedAt": "2026-05-08T18:38:12.863Z"
    },
    {
      "id": "870125",
      "title": "Projekt ,,Erlebnissportplatz Prösen‘‘ des SV 1919 Prösen bei „machen!2023“ ausgezeichnet",
      "url": "https://www.gemeinde-roederland.de/news/2/870125/sport/projekt-erlebnissportplatz-prösen-des-sv-1919-prösen-bei-machen2023-ausgezeichnet.html",
      "description": "Am 26.09.2023 wurden in Berlin die Preisträger des Wettbewerbes „machen!2023“ ausgezeichnet. Zu den 106 Preistragenden gehörte auch das Projekt ,,Erlebnissportplatz‘‘ des SV 1919 aus ...  [mehr]",
      "fetchedAt": "2026-05-08T18:37:39.639Z",
      "publishedAt": "2023-09-29T00:00:00.000Z",
      "updatedAt": "2026-05-08T18:38:12.863Z"
    },
    {
      "id": "861106",
      "title": "Gemeindeverwaltung geschlossen",
      "url": "https://www.gemeinde-roederland.de/news/1/861106/nachrichten/gemeindeverwaltung-geschlossen.html",
      "description": "Am Montag, dem 2. und 30. Oktober 2023 bleibt die Verwaltung geschlossen!     [mehr]",
      "fetchedAt": "2026-05-08T18:37:39.639Z",
      "publishedAt": "2023-09-01T00:00:00.000Z",
      "updatedAt": "2026-05-08T18:38:12.863Z"
    },
    {
      "id": "841685",
      "title": "Achtung! Arbeiten am Stromnetz in Saathain",
      "url": "https://www.gemeinde-roederland.de/news/1/841685/nachrichten/achtung-arbeiten-am-stromnetz-in-saathain.html",
      "description": "Der Stromnetzbetreiber MITNETZ Strom informiert:   Sehr geehrte Kundin, sehr geehrter Kunde,   am Mittwoch, dem 28. Juni 2023 von 08:00 bis ca. 09:00 Uhr und von 13:00 bis ca. 14:00 Uhr erfolgen ...  [mehr]",
      "fetchedAt": "2026-05-08T18:37:39.639Z",
      "publishedAt": "2023-06-23T00:00:00.000Z",
      "updatedAt": "2026-05-08T18:38:12.863Z"
    },
    {
      "id": "838776",
      "title": "Startschuss für den KulturPass",
      "url": "https://www.gemeinde-roederland.de/news/1/838776/nachrichten/startschuss-für-den-kulturpass.html",
      "description": "Jugendliche in Südbrandenburg können 200 Euro für kulturelle Angebote ab sofort nutzen   Junge Menschen, die im Jahr 2023 ihren 18. Geburtstag feiern, erhalten mit dem KulturPass ein Budget von ...  [mehr]",
      "fetchedAt": "2026-05-08T18:37:39.639Z",
      "publishedAt": "2023-06-15T00:00:00.000Z",
      "updatedAt": "2026-05-08T18:38:12.863Z"
    },
    {
      "id": "832852",
      "title": "Ankündigung von Maßnahmen der Gewässerunterhaltung",
      "url": "https://www.gemeinde-roederland.de/news/1/832852/nachrichten/ankündigung-von-maßnahmen-der-gewässerunterhaltung.html",
      "description": "Der Gewässerverband Kleine Elster - Pulsnitz informiert:   In der Zeit vom 15. Juli 2023 bis zum 28. Februar 2024 führen der Gewässerverband Kleine Elster-Pulsnitz und die von uns beauftragten ...  [mehr]",
      "fetchedAt": "2026-05-08T18:37:39.639Z",
      "publishedAt": "2023-05-24T00:00:00.000Z",
      "updatedAt": "2026-05-08T18:38:12.863Z"
    },
    {
      "id": "828819",
      "title": "Online-Portal zur Beantragung von Härtefallhilfen für Energiekosten freigeschaltet!",
      "url": "https://www.gemeinde-roederland.de/news/1/828819/nachrichten/online-portal-zur-beantragung-von-härtefallhilfen-für-energiekosten-freigeschaltet.html",
      "description": "Das Ministerium für Wirtschaft, Arbeit und Energie informiert: seit dem 8. Mai 2023 können Härtefallhilfen für Energiekosten privater Haushalte über das Antragsportal der ILB beantragt werden. ...  [mehr]",
      "fetchedAt": "2026-05-08T18:37:39.639Z",
      "publishedAt": "2023-05-09T00:00:00.000Z",
      "updatedAt": "2026-05-08T18:38:12.863Z"
    },
    {
      "id": "500958",
      "title": "Umtauschpflicht für Führerscheine",
      "url": "https://www.gemeinde-roederland.de/news/1/500958/nachrichten/umtauschpflicht-für-führerscheine.html",
      "description": "Alte Chipkartenführerscheine, welche von 1999 bis 2001 ausgestellt wurden, müssen bis zum 19.01.2026 umgetauscht werden.   Eine Übersicht über die jeweiligen Umtauschfristen finden Sie in dem ...  [mehr]",
      "fetchedAt": "2026-05-08T18:37:39.639Z",
      "publishedAt": "2025-12-30T00:00:00.000Z",
      "updatedAt": "2026-05-08T18:38:12.863Z"
    }
  ]
}