{
  "updatedAt": "2026-05-08T17:59:22.475Z",
  "items": [
    {
      "id": "heideblick-amtsblatt-2025-07",
      "title": "Amtsblatt Nr. 7/2025",
      "url": "https://daten.verwaltungsportal.de/dateien/gazette/8/4/2/0/7/Gemeindeblatt_11-25.pdf",
      "publishedAt": "2025-11-19T00:00:00.000Z",
      "fetchedAt": "2026-05-08T17:59:22.473Z"
    },
    {
      "id": "heideblick-amtsblatt-2025-06",
      "title": "Amtsblatt Nr. 6/2025",
      "url": "https://daten.verwaltungsportal.de/dateien/gazette/8/4/1/2/0/Gemeindeblatt_06-25-3.pdf",
      "publishedAt": "2025-10-16T00:00:00.000Z",
      "fetchedAt": "2026-05-08T17:59:22.473Z"
    },
    {
      "id": "heideblick-amtsblatt-2025-05",
      "title": "Amtsblatt Nr. 5/2025",
      "url": "https://daten.verwaltungsportal.de/dateien/gazette/8/4/1/1/9/Gemeindeblatt_05_2025-4.pdf",
      "publishedAt": "2025-09-16T00:00:00.000Z",
      "fetchedAt": "2026-05-08T17:59:22.473Z"
    },
    {
      "id": "heideblick-amtsblatt-2025-04",
      "title": "Amtsblatt Nr. 4/2025",
      "url": "https://daten.verwaltungsportal.de/dateien/gazette/8/4/1/1/8/Gemeindeblatt_08-2025-1.pdf",
      "publishedAt": "2025-08-20T00:00:00.000Z",
      "fetchedAt": "2026-05-08T17:59:22.473Z"
    },
    {
      "id": "heideblick-amtsblatt-2025-03",
      "title": "Amtsblatt Nr. 3/2025",
      "url": "https://daten.verwaltungsportal.de/dateien/gazette/8/4/1/1/7/Gemeindeblatt_Juli_2025-1.pdf",
      "publishedAt": "2025-07-22T00:00:00.000Z",
      "fetchedAt": "2026-05-08T17:59:22.473Z"
    },
    {
      "id": "heideblick-amtsblatt-2025-02",
      "title": "Amtsblatt Nr. 2/2025",
      "url": "https://daten.verwaltungsportal.de/dateien/gazette/8/4/1/1/6/Gemeindeblatt_Juni_25-1.pdf",
      "publishedAt": "2025-06-12T00:00:00.000Z",
      "fetchedAt": "2026-05-08T17:59:22.473Z"
    },
    {
      "id": "heideblick-amtsblatt-2025-01",
      "title": "Amtsblatt Nr. 1/2025",
      "url": "https://daten.verwaltungsportal.de/dateien/gazette/8/4/1/1/5/Gemeindeblatt_05_2025-3.pdf",
      "publishedAt": "2025-05-21T00:00:00.000Z",
      "fetchedAt": "2026-05-08T17:59:22.473Z"
    },
    {
      "id": "heideblick-amtsblatt-2025-4a",
      "title": "Amtsblatt Nr. 4a/2025",
      "url": "https://daten.verwaltungsportal.de/dateien/gazette/8/0/2/0/1/Entwurf_Amtsblatt_April_2025.pdf",
      "publishedAt": "2025-04-15T00:00:00.000Z",
      "fetchedAt": "2026-05-08T17:59:22.473Z"
    },
    {
      "id": "heideblick-amtsblatt-2024-12",
      "title": "Amtsblatt Nr. 12/2024",
      "url": "https://daten.verwaltungsportal.de/dateien/gazette/7/7/6/0/5/Amtsblatt_Dez._24.pdf",
      "publishedAt": "2024-12-18T00:00:00.000Z",
      "fetchedAt": "2026-05-08T17:59:22.473Z"
    },
    {
      "id": "heideblick-amtsblatt-2024-11",
      "title": "Amtsblatt Nr. 11/2024",
      "url": "https://daten.verwaltungsportal.de/dateien/gazette/7/7/1/5/4/Amtsblatt.November.pdf",
      "publishedAt": "2024-11-20T00:00:00.000Z",
      "fetchedAt": "2026-05-08T17:59:22.473Z"
    },
    {
      "id": "heideblick-amtsblatt-2024-10",
      "title": "Amtsblatt Nr. 10/2024",
      "url": "https://daten.verwaltungsportal.de/dateien/gazette/7/6/6/9/4/Amtsblatt_Oktober_24.pdf",
      "publishedAt": "2024-10-23T00:00:00.000Z",
      "fetchedAt": "2026-05-08T17:59:22.473Z"
    },
    {
      "id": "heideblick-amtsblatt-2024-09",
      "title": "Amtsblatt Nr. 9/2024",
      "url": "https://daten.verwaltungsportal.de/dateien/gazette/7/6/1/1/9/Amtsblatt_September_2024.pdf",
      "publishedAt": "2024-09-18T00:00:00.000Z",
      "fetchedAt": "2026-05-08T17:59:22.473Z"
    },
    {
      "id": "heideblick-amtsblatt-2024-08",
      "title": "Amtsblatt Nr. 8/2024",
      "url": "https://daten.verwaltungsportal.de/dateien/gazette/7/5/6/1/4/Amtsblatt_08.pdf",
      "publishedAt": "2024-08-21T00:00:00.000Z",
      "fetchedAt": "2026-05-08T17:59:22.473Z"
    },
    {
      "id": "heideblick-amtsblatt-2024-07",
      "title": "Amtsblatt Nr. 7/2024",
      "url": "https://daten.verwaltungsportal.de/dateien/gazette/7/4/6/5/4/Amtsblatt_Juli_2024.pdf",
      "publishedAt": "2024-07-24T00:00:00.000Z",
      "fetchedAt": "2026-05-08T17:59:22.473Z"
    }
  ]
}